client_profiler/__init__.py
client_profiler/__main__.py
client_profiler/profiler.py
client_profiler_NovEf-0.1.dist-info/METADATA
client_profiler_NovEf-0.1.dist-info/WHEEL
client_profiler_NovEf-0.1.dist-info/top_level.txt
client_profiler_NovEf-0.1.dist-info/RECORD
