Metadata-Version: 2.1
Name: client_profiler_NovEf
Version: 0.1
Summary: Это client_profiler, делай с ним че хочешь
Author: Novoselov Efim
Author-email: Novoselov Efim <myemail@example.com>
License: MIT
Requires-Python: >=3.10
Requires-Dist: requests>=2.25.1
Requires-Dist: numpy>=1.19.2
Requires-Dist: pandas>=2.2.3
